{
  "-NP9D9W09TavirEn2awr": {
    "firebaseKey": "-NP9D9W09TavirEn2awr",
    "uid": "7Mh8g7uxf1bQTgbnGLonylVleBT2",
    "volume_name": "FLCL",
    "isOwned": false,
    "series_id": "-NO_dCeN17VK6yR-9rJF"
  },
  "-NP9D9W3h2mp27eTmGAt": {
    "firebaseKey": "-NP9D9W3h2mp27eTmGAt",
    "uid": "7Mh8g7uxf1bQTgbnGLonylVleBT2",
    "volume_name": "Hustler White",
    "isOwned": true,
    "series_id": "-NO_dCeK5uO8Rlir_GBd"
  },
  "-NP9D9W6Jb1vPuvF1ohU": {
    "firebaseKey": "-NP9D9W6Jb1vPuvF1ohU",
    "uid": "7Mh8g7uxf1bQTgbnGLonylVleBT2",
    "volume_name": "Thorn in the Heart, The",
    "isOwned": false,
    "series_id": "-NO_dCeUu9Q8vE2ztASR"
  },
  "-NP9D9WAXn8E-qWKDrrq": {
    "firebaseKey": "-NP9D9WAXn8E-qWKDrrq",
    "uid": "7Mh8g7uxf1bQTgbnGLonylVleBT2",
    "volume_name": "StarStruck",
    "isOwned": true,
    "series_id": "-NO_dCeROE6evVxfBq9J"
  },
  "-NP9D9WDudNb7hhu-Eom": {
    "firebaseKey": "-NP9D9WDudNb7hhu-Eom",
    "uid": "7Mh8g7uxf1bQTgbnGLonylVleBT2",
    "volume_name": "Wichita",
    "isOwned": true,
    "series_id": "-NO_dCeK5uO8Rlir_GBd"
  },
  "-NP9D9WFjpQQ30odgbJB": {
    "firebaseKey": "-NP9D9WFjpQQ30odgbJB",
    "uid": "7Mh8g7uxf1bQTgbnGLonylVleBT2",
    "volume_name": "Despicable Me",
    "isOwned": true,
    "series_id": "-NO_dCeK5uO8Rlir_GBd"
  },
  "-NP9D9WIupiZoGeuO_bB": {
    "firebaseKey": "-NP9D9WIupiZoGeuO_bB",
    "uid": "7Mh8g7uxf1bQTgbnGLonylVleBT2",
    "volume_name": "Navigators, The",
    "isOwned": false,
    "series_id": "-NO_dCeGEfKbotfoM5uf"
  },
  "-NP9D9WK-78gJ7JFQWYn": {
    "firebaseKey": "-NP9D9WK-78gJ7JFQWYn",
    "uid": "7Mh8g7uxf1bQTgbnGLonylVleBT2",
    "volume_name": "Regular Lovers (Amants réguliers, Les)",
    "isOwned": false,
    "series_id": "-NO_dCeGEfKbotfoM5uf"
  },
  "-NP9D9WMFutsHq-GYdvx": {
    "firebaseKey": "-NP9D9WMFutsHq-GYdvx",
    "uid": "7Mh8g7uxf1bQTgbnGLonylVleBT2",
    "volume_name": "Alien Outpost",
    "isOwned": false,
    "series_id": "-NO_dCeROE6evVxfBq9J"
  },
  "-NP9D9WOt90CCAj5MXRd": {
    "firebaseKey": "-NP9D9WOt90CCAj5MXRd",
    "uid": "7Mh8g7uxf1bQTgbnGLonylVleBT2",
    "volume_name": "Happy Feet Two",
    "isOwned": false,
    "series_id": "-NO_dCeN17VK6yR-9rJF"
  },
  "-NP9D9WQek4aLd581IHu": {
    "firebaseKey": "-NP9D9WQek4aLd581IHu",
    "uid": "7Mh8g7uxf1bQTgbnGLonylVleBT2",
    "volume_name": "Palmetto",
    "isOwned": false,
    "series_id": "-NO_dCeROE6evVxfBq9J"
  },
  "-NP9D9WTQpByNhfnw60j": {
    "firebaseKey": "-NP9D9WTQpByNhfnw60j",
    "uid": "7Mh8g7uxf1bQTgbnGLonylVleBT2",
    "volume_name": "The Incident",
    "isOwned": false,
    "series_id": "-NO_dCeK5uO8Rlir_GBd"
  },
  "-NP9D9WVlIo_SCx5NRPZ": {
    "firebaseKey": "-NP9D9WVlIo_SCx5NRPZ",
    "uid": "7Mh8g7uxf1bQTgbnGLonylVleBT2",
    "volume_name": "Wizard of Oz, The",
    "isOwned": false,
    "series_id": "-NO_dCeK5uO8Rlir_GBd"
  },
  "-NP9D9WXGvaJhrzoVvpD": {
    "firebaseKey": "-NP9D9WXGvaJhrzoVvpD",
    "uid": "7Mh8g7uxf1bQTgbnGLonylVleBT2",
    "volume_name": "And Soon the Darkness",
    "isOwned": false,
    "series_id": "-NO_dCeUu9Q8vE2ztASR"
  },
  "-NP9D9W_WSmAZwsCQ_AB": {
    "firebaseKey": "-NP9D9W_WSmAZwsCQ_AB",
    "uid": "7Mh8g7uxf1bQTgbnGLonylVleBT2",
    "volume_name": "Abandon",
    "isOwned": true,
    "series_id": "-NO_dCeN17VK6yR-9rJF"
  },
  "-NP9D9WbFpKYAE_hWHm6": {
    "firebaseKey": "-NP9D9WbFpKYAE_hWHm6",
    "uid": "7Mh8g7uxf1bQTgbnGLonylVleBT2",
    "volume_name": "Skyfall",
    "isOwned": false,
    "series_id": "-NO_dCeUu9Q8vE2ztASR"
  },
  "-NP9D9WeJdbwyBEOxYEJ": {
    "firebaseKey": "-NP9D9WeJdbwyBEOxYEJ",
    "uid": "7Mh8g7uxf1bQTgbnGLonylVleBT2",
    "volume_name": "Victor Sjöström: Ett porträtt",
    "isOwned": false,
    "series_id": "-NO_dCeGEfKbotfoM5uf"
  },
  "-NP9D9WgOHiimlp0fcuZ": {
    "firebaseKey": "-NP9D9WgOHiimlp0fcuZ",
    "uid": "7Mh8g7uxf1bQTgbnGLonylVleBT2",
    "volume_name": "Essex Boys",
    "isOwned": true,
    "series_id": "-NO_dCeN17VK6yR-9rJF"
  },
  "-NP9D9WiS6tOZJQW8J2M": {
    "firebaseKey": "-NP9D9WiS6tOZJQW8J2M",
    "uid": "7Mh8g7uxf1bQTgbnGLonylVleBT2",
    "volume_name": "Hideous Sun Demon, The",
    "isOwned": false,
    "series_id": "-NO_dCeN17VK6yR-9rJF"
  },
  "-NP9D9WlErZIIwWV3Qrh": {
    "firebaseKey": "-NP9D9WlErZIIwWV3Qrh",
    "uid": "7Mh8g7uxf1bQTgbnGLonylVleBT2",
    "volume_name": "Girlhood",
    "isOwned": false,
    "series_id": "-NO_dCeROE6evVxfBq9J"
  },
  "-NP9D9WpZy-mbohUByCE": {
    "firebaseKey": "-NP9D9WpZy-mbohUByCE",
    "uid": "7Mh8g7uxf1bQTgbnGLonylVleBT2",
    "volume_name": "Megan Is Missing",
    "isOwned": true,
    "series_id": "-NO_dCeGEfKbotfoM5uf"
  },
  "-NP9D9WrtEetqahlpkge": {
    "firebaseKey": "-NP9D9WrtEetqahlpkge",
    "uid": "7Mh8g7uxf1bQTgbnGLonylVleBT2",
    "volume_name": "Go for It",
    "isOwned": false,
    "series_id": "-NO_dCeROE6evVxfBq9J"
  },
  "-NP9D9WuJzE42AD8P5sG": {
    "firebaseKey": "-NP9D9WuJzE42AD8P5sG",
    "uid": "7Mh8g7uxf1bQTgbnGLonylVleBT2",
    "volume_name": "Blaise Pascal",
    "isOwned": true,
    "series_id": "-NO_dCeK5uO8Rlir_GBd"
  },
  "-NP9D9WwPGQFk6Q3E26c": {
    "firebaseKey": "-NP9D9WwPGQFk6Q3E26c",
    "uid": "7Mh8g7uxf1bQTgbnGLonylVleBT2",
    "volume_name": "Flashback",
    "isOwned": true,
    "series_id": "-NO_dCeN17VK6yR-9rJF"
  },
  "-NP9D9Wz40aV4pHJ3fKC": {
    "firebaseKey": "-NP9D9Wz40aV4pHJ3fKC",
    "uid": "7Mh8g7uxf1bQTgbnGLonylVleBT2",
    "volume_name": "Devil Bat, The",
    "isOwned": false,
    "series_id": "-NO_dCeK5uO8Rlir_GBd"
  }
}
